{
  "destinos": [
    { "id": 1, "empresa": "VIA VAREJO S/A", "endereco" : "Rua Humberto Scigliano, 61 - Parque Munhoz" },
    { "id": 2, "empresa": "TECH SHOP.COM.BR COM. E SERV", "endereco" : "Av. Paulista, 1374, São Paulo, SP" },
    { "id": 3, "empresa": "MAKFORTE COM. MAQS. LTDA ME", "endereco" : "avenida santo amaro, 1000" },
  ],
  "comments": [
    { "id": 1, "body": "some comment", "postId": 1 },
    { "id": 2, "body": "some comment", "postId": 1 }
  ],
  "profile": {
    "name": "Api App Track Singer"
  }
}
